versionnumber/__init__.py
versionnumber/semantic/__init__.py
versionnumber/semantic/v1.py
versionnumber/semantic/v2.py
versionnumber-0.1.0.dist-info/LICENSE
versionnumber-0.1.0.dist-info/METADATA
versionnumber-0.1.0.dist-info/WHEEL
versionnumber-0.1.0.dist-info/top_level.txt
versionnumber-0.1.0.dist-info/RECORD
