Metadata-Version: 2.1
Name: versionnumber
Version: 0.1.0
Summary: A version number manipulation library
Author-email: "Duy N. H. A." <me@duynha.dev>
License: MIT License
Project-URL: homepage, https://www.duynha.dev/projects/versionnumber
Project-URL: documentation, https://readthedocs.org
Project-URL: repository, https://github.com/
Project-URL: changelog, https://github.com/
Keywords: Networking,IP,IPv4,IPv6
Classifier: Development Status :: 1 - Planning
Classifier: Intended Audience :: Developers
Classifier: Programming Language :: Python
Classifier: Programming Language :: Python :: 3
Classifier: Programming Language :: Python :: 3 :: Only
Classifier: Programming Language :: Python :: 3.9
Classifier: Programming Language :: Python :: 3.10
Classifier: Programming Language :: Python :: 3.11
Classifier: Programming Language :: Python :: 3.12
Classifier: Operating System :: OS Independent
Classifier: License :: OSI Approved :: MIT License
Classifier: Topic :: Documentation
Classifier: Topic :: Documentation :: Sphinx
Classifier: Topic :: Software Development
Classifier: Topic :: Software Development :: Libraries
Classifier: Topic :: Utilities
Classifier: Typing :: Typed
Requires-Python: >=3.9
License-File: LICENSE
Provides-Extra: build
Requires-Dist: build ; extra == 'build'
Provides-Extra: develop
Requires-Dist: versionnumber[lint] ; extra == 'develop'
Requires-Dist: versionnumber[test] ; extra == 'develop'
Requires-Dist: versionnumber[build] ; extra == 'develop'
Requires-Dist: versionnumber[publish] ; extra == 'develop'
Provides-Extra: lint
Requires-Dist: black ; extra == 'lint'
Requires-Dist: flake8 ; extra == 'lint'
Requires-Dist: flake8-pyproject ; extra == 'lint'
Requires-Dist: isort ; extra == 'lint'
Requires-Dist: mypy ; extra == 'lint'
Requires-Dist: pylint ; extra == 'lint'
Provides-Extra: publish
Requires-Dist: twine ; extra == 'publish'
Provides-Extra: test
Requires-Dist: pytest ; extra == 'test'
